fancylit/__init__.py
fancylit/modeling/__init__.py
fancylit/modeling/yellowbrick_funcs.py
fancylit/stats/__init__.py
fancylit/stats/data_stats.py
fancylit/viz/__init__.py
fancylit/viz/charts.py
fancylit-0.0.2.dist-info/LICENSE
fancylit-0.0.2.dist-info/METADATA
fancylit-0.0.2.dist-info/WHEEL
fancylit-0.0.2.dist-info/top_level.txt
fancylit-0.0.2.dist-info/RECORD
